{
    "$schema": "http://json-schema.org/draft-07/schema#",
    "$id": "http://datamodel.tmforum.org/MefPlaceRef.schema.jsonOrValue.schema.json",
    "$version":"5.0",
    "title": "MefPlaceRef",
    "definitions": {
      "MefPlaceRef": {
        "$id": "#MefPlaceRef",
        "type": "object",
        "description": "Place Reference - Place defines the places where the products' action must be done.",
        "allOf": [
          {
            "$ref": "../../../../Gc/Common/GcPlaceRef.schema.json#/GcPlaceRef"
          },
          {
            "$ref": "../../../../Core/EntityRef.schema.json#/EntityRef"
          }
        ]
      }
    }
  }
  